setup.cfg
setup.py
bootstrap_datepicker/__init__.py
bootstrap_datepicker/widgets.py
django_bootstrap_datepicker_widget.egg-info/PKG-INFO
django_bootstrap_datepicker_widget.egg-info/SOURCES.txt
django_bootstrap_datepicker_widget.egg-info/dependency_links.txt
django_bootstrap_datepicker_widget.egg-info/top_level.txt