Metadata-Version: 1.1
Name: django-bootstrap-datepicker-widget
Version: 0.1
Summary: Bootstrap 3 and 4 compatible Datepicker widget for Django.
Home-page: https://github.com/jackweath/django-bootstrap-datepicker
Author: Nakahara Kunihiko/Samuel Colvin/Jack Weatherilt
Author-email: nakahara.kunihiko@gmail.com/s@muelcolvin.com/jackweatherilt@outlook.com
License: Apache License 2.0
Platform: UNKNOWN
Classifier: Intended Audience :: Developers
Classifier: License :: OSI Approved :: Apache Software License
Classifier: Programming Language :: Python
Classifier: Programming Language :: Python :: 2
Classifier: Programming Language :: Python :: 3
Classifier: Operating System :: OS Independent
Classifier: Topic :: Software Development :: Libraries
Classifier: Topic :: Utilities
Classifier: Environment :: Web Environment
Classifier: Framework :: Django
